needle_track/__init__.py
needle_track/__main__.py
needle_track/data_injest.py
needle_track/database_manager.py
needle_track-0.1.6.dist-info/METADATA
needle_track-0.1.6.dist-info/WHEEL
needle_track-0.1.6.dist-info/entry_points.txt
needle_track-0.1.6.dist-info/top_level.txt
needle_track-0.1.6.dist-info/RECORD
