Metadata-Version: 2.4
Name: needle-track
Version: 0.1.6
Summary: Transient Recognition, Annotation, and Classification Kit
Home-page: https://github.com/XinyueSheng2019/NEEDLE-TRACK
Author: Xinyue Sheng
Author-email: XinyueSheng@outlook.com
Project-URL: Bug Reports, https://github.com/XinyueSheng2019/NEEDLE-TRACK/issues
Project-URL: Source, https://github.com/XinyueSheng2019/NEEDLE-TRACK
Classifier: Programming Language :: Python :: 3
Classifier: License :: OSI Approved :: MIT License
Classifier: Operating System :: OS Independent
Classifier: Development Status :: 4 - Beta
Classifier: Intended Audience :: Science/Research
Classifier: Topic :: Scientific/Engineering :: Astronomy
Requires-Python: >=3.11
Requires-Dist: numpy>=2.0.0
Requires-Dist: pandas>=2.0.0
Requires-Dist: astropy>=7.0.0
Requires-Dist: lasair>=0.1.1
Requires-Dist: requests>=2.30.0
Dynamic: author
Dynamic: author-email
Dynamic: classifier
Dynamic: description
Dynamic: description-content-type
Dynamic: home-page
Dynamic: project-url
Dynamic: requires-dist
Dynamic: requires-python
Dynamic: summary
